[
    {
        "contestId": 1974,
        "index": "B",
        "rating": 800,
        "tags": [
            "implementation",
            "sortings",
            "strings"
        ],
        "id": 261908769,
        "programmingLanguage": "Java 21",
        "verdict": "OK"
    },
    {
        "contestId": 1974,
        "index": "A",
        "rating": 800,
        "tags": [
            "greedy",
            "math"
        ],
        "id": 261871761,
        "programmingLanguage": "Java 21",
        "verdict": "OK"
    },
    {
        "contestId": 1974,
        "index": "A",
        "rating": 800,
        "tags": [
            "greedy",
            "math"
        ],
        "id": 261859535,
        "programmingLanguage": "Java 21",
        "verdict": "WRONG_ANSWER"
    },
    {
        "contestId": 1968,
        "index": "B",
        "rating": 800,
        "tags": [
            "greedy",
            "two pointers"
        ],
        "id": 259221110,
        "programmingLanguage": "Java 21",
        "verdict": "OK"
    },
    {
        "contestId": 1968,
        "index": "A",
        "rating": 800,
        "tags": [
            "brute force",
            "math",
            "number theory"
        ],
        "id": 259174818,
        "programmingLanguage": "Java 21",
        "verdict": "OK"
    },
    {
        "contestId": 1950,
        "index": "A",
        "rating": 800,
        "tags": [
            "implementation"
        ],
        "id": 253689860,
        "programmingLanguage": "Java 21",
        "verdict": "OK"
    },
    {
        "contestId": 1950,
        "index": "A",
        "rating": 800,
        "tags": [
            "implementation"
        ],
        "id": 253676249,
        "programmingLanguage": "Java 21",
        "verdict": "WRONG_ANSWER"
    },
    {
        "contestId": 71,
        "index": "A",
        "points": 500.0,
        "rating": 800,
        "tags": [
            "strings"
        ],
        "id": 253093815,
        "programmingLanguage": "Java 21",
        "verdict": "OK"
    },
    {
        "contestId": 71,
        "index": "A",
        "points": 500.0,
        "rating": 800,
        "tags": [
            "strings"
        ],
        "id": 253093620,
        "programmingLanguage": "Java 21",
        "verdict": "COMPILATION_ERROR"
    },
    {
        "contestId": 282,
        "index": "A",
        "points": 500.0,
        "rating": 800,
        "tags": [
            "implementation"
        ],
        "id": 253034201,
        "programmingLanguage": "Java 21",
        "verdict": "OK"
    },
    {
        "contestId": 282,
        "index": "A",
        "points": 500.0,
        "rating": 800,
        "tags": [
            "implementation"
        ],
        "id": 253031835,
        "programmingLanguage": "GNU C11",
        "verdict": "COMPILATION_ERROR"
    }
]