{
    "lastName": "Tulsyan",
    "country": "India",
    "lastOnlineTimeSeconds": 1718212548,
    "city": "Gorakhpur",
    "rating": 1264,
    "friendOfCount": 4,
    "titlePhoto": "https://userpic.codeforces.org/no-title.jpg",
    "handle": "vtulsyan04",
    "avatar": "https://userpic.codeforces.org/no-avatar.jpg",
    "firstName": "Vanshika",
    "contribution": 0,
    "organization": "IIT KGP",
    "rank": "pupil",
    "maxRating": 1264,
    "registrationTimeSeconds": 1702389210,
    "maxRank": "pupil"
}